README.md
setup.py
cqt_nsgt_pytorch/CQT_nsgt.py
cqt_nsgt_pytorch/__init__.py
cqt_nsgt_pytorch/fscale.py
cqt_nsgt_pytorch/nsdual.py
cqt_nsgt_pytorch/nsgfwin.py
cqt_nsgt_pytorch/util.py
cqt_nsgt_pytorch.egg-info/PKG-INFO
cqt_nsgt_pytorch.egg-info/SOURCES.txt
cqt_nsgt_pytorch.egg-info/dependency_links.txt
cqt_nsgt_pytorch.egg-info/requires.txt
cqt_nsgt_pytorch.egg-info/top_level.txt